ttask_manager/__init__.py
ttask_manager/ttask_manager.py
ttask_manager-1.1.5.dist-info/METADATA
ttask_manager-1.1.5.dist-info/WHEEL
ttask_manager-1.1.5.dist-info/licenses/LICENSE
ttask_manager-1.1.5.dist-info/RECORD
