Metadata-Version: 2.4
Name: ttask_manager
Version: 1.1.5
Summary: A simple task management package.
Project-URL: Homepage, https://github.com/tahadnan/ttask-manager
Project-URL: Bug Tracker, https://github.com/tahadnan/ttask-manager/issues
Author-email: Taha Yasser Adnan <tahadnan.101@gmail.com>
License-File: LICENSE
Classifier: License :: OSI Approved :: MIT License
Classifier: Operating System :: OS Independent
Classifier: Programming Language :: Python :: 3
Requires-Python: >=3.8
Requires-Dist: rich
